README.md
setup.cfg
setup.py
tg263/__init__.py
tg263/dictionary.py
tg263/exceptions.py
tg263/structure.py
tg263/structures.py
tg263.egg-info/PKG-INFO
tg263.egg-info/SOURCES.txt
tg263.egg-info/dependency_links.txt
tg263.egg-info/top_level.txt