Metadata-Version: 2.1
Name: tg263
Version: 0.2.0
Summary: TG263 implementation
Home-page: https://gitlab.physmed.chudequebec.ca/gacou54/tg263
Author: Gabriel Couture
Author-email: gacou54@gmail.com
License: MIT
Platform: UNKNOWN
Classifier: Development Status :: 3 - Alpha
Classifier: Intended Audience :: Healthcare Industry
Classifier: Intended Audience :: Science/Research
Classifier: License :: OSI Approved :: MIT License
Classifier: Operating System :: OS Independent
Classifier: Programming Language :: Python :: 3 :: Only
Classifier: Programming Language :: Python :: 3.6
Classifier: Programming Language :: Python :: 3.7
